chinese_regular_expression/__init__.py
chinese_regular_expression/规律.py
chinese_regular_expression-0.0.2.dist-info/METADATA
chinese_regular_expression-0.0.2.dist-info/WHEEL
chinese_regular_expression-0.0.2.dist-info/licenses/LICENSE
chinese_regular_expression-0.0.2.dist-info/RECORD
