Metadata-Version: 2.3
Name: chinese_regular_expression
Version: 0.0.2
Summary: 中文正则表达式
Project-URL: Homepage, https://gitee.com/Program-in-Chinese/regular-expression
Project-URL: Bug Tracker, https://gitee.com/Program-in-Chinese/regular-expression/issues
Author-email: 吴烜 <nobodxbodon.github@gmail.com>
Classifier: License :: OSI Approved :: MIT License
Classifier: Operating System :: OS Independent
Classifier: Programming Language :: Python :: 3
Requires-Python: >=3.7
